Workbook
Name ExternalData_1: 'CONTAINER_COST_MONTH'!#REF!
Name ExternalData_1: DEMAND_FG!#REF!

Sheet Bill of Materials
A1: Level | B1: Vehicle Type | C1: Assembly Code | D1: Assembly Name | E1: Parent Code | F1: Quantity | G1: Unit | H1: Supplier | I1: Origin | J1: Product Item Code
A2: 1 | B2: Sedan | C2: LSCENSD0001 | D2: Engine - SD | F2: 1 | G2: set | H2: LSC Automobile JP | I2: Japan | J2: SEDAN_001
A3: 1 | B3: Sedan | C3: LSCTRSD0002 | D3: Transmission - SD | F3: 1 | G3: set | H3: LSC Trans VN | I3: Vietnam | J3: SEDAN_001
A4: 1 | B4: Sedan | C4: LSCCHSD0003 | D4: Chassis - SD | F4: 1 | G4: set | H4: LSC Automobile JP | I4: Japan | J4: SEDAN_001
A5: 1 | B5: Sedan | C5: LSCBDSD0004 | D5: Body - SD | F5: 1 | G5: set | H5: LSC Automobile JP | I5: Japan | J5: SEDAN_001
A6: 1 | B6: Sedan | C6: LSCINSD0005 | D6: Interior - SD | F6: 1 | G6: set | H6: VN Interiors Ltd | I6: Vietnam | J6: SEDAN_001
A7: 1 | B7: Sedan Luxury | C7: LSCENSD0001-LX | D7: Engine - SD - LX | F7: 1 | G7: set | H7: LSC Automobile JP | I7: Japan | J7: SEDAN_LUXURY_001
A8: 1 | B8: Sedan Luxury | C8: LSCTRSD0002-LX | D8: Transmission - SD - LX | F8: 1 | G8: set | H8: LSC Trans VN | I8: Vietnam | J8: SEDAN_LUXURY_001
A9: 1 | B9: Sedan Luxury | C9: LSCCHSD0003-LX | D9: Chassis - SD - LX | F9: 1 | G9: set | H9: LSC Automobile JP | I9: Japan | J9: SEDAN_LUXURY_001
A10: 1 | B10: Sedan Luxury | C10: LSCBDSD0004-LX | D10: Body - SD - LX | F10: 1 | G10: set | H10: LSC Automobile JP | I10: Japan | J10: SEDAN_LUXURY_001
A11: 1 | B11: Sedan Luxury | C11: LSCINSD0005-LX | D11: Interior - SD - LX | F11: 1 | G11: set | H11: VN Interiors Ltd | I11: Vietnam | J11: SEDAN_LUXURY_001
A12: 1 | B12: SUV | C12: LSCENSV0006 | D12: Engine - SUV | F12: 1 | G12: set | H12: LSC Automobile JP | I12: Japan | J12: SUV_001
A13: 1 | B13: SUV | C13: LSCTRSV0007 | D13: Transmission - SUV | F13: 1 | G13: set | H13: LSC Trans VN | I13: Vietnam | J13: SUV_001
... A21: 1 | B21: SUV Luxury | C21: LSCINSV0010-LX | D21: Interior - SUV - LX | F21: 1 | G21: set | H21: VN Interiors Ltd | I21: Vietnam | J21: SUV_LUXURY_001
A22: 2 | B22: Sedan | C22: CYL-SD | D22: Cylinder Block - SD | E22: LSCENSD0001 | F22: 1 | G22: set | H22: LSC Automobile JP | I22: Japan | J22: SEDAN_001
A23: 2 | B23: Sedan | C23: PIST-SD | D23: Pistons - SD | E23: LSCENSD0001 | F23: 4 | G23: pcs | H23: LSC Automobile JP | I23: Japan | J23: SEDAN_001
A24: 2 | B24: Sedan | C24: GEAR-SD | D24: Gear Set - SD | E24: LSCTRSD0002 | F24: 1 | G24: set | H24: LSC Trans VN | I24: Vietnam | J24: SEDAN_001
A25: 2 | B25: Sedan | C25: SYNC-SD | D25: Synchronizer - SD | E25: LSCTRSD0002 | F25: 1 | G25: pcs | H25: LSC Trans VN | I25: Vietnam | J25: SEDAN_001
A26: 2 | B26: Sedan | C26: FRAME-SD | D26: Chassis Frame - SD | E26: LSCCHSD0003 | F26: 1 | G26: set | H26: LSC Automobile JP | I26: Japan | J26: SEDAN_001
A27: 2 | B27: Sedan | C27: MEMBER-SD | D27: Cross Member - SD | E27: LSCCHSD0003 | F27: 1 | G27: set | H27: LSC Automobile JP | I27: Japan | J27: SEDAN_001
A28: 2 | B28: Sedan | C28: DOOR-SD | D28: Door - SD | E28: LSCBDSD0004 | F28: 5 | G28: pcs | H28: LSC Automobile JP | I28: Japan | J28: SEDAN_001
A29: 2 | B29: Sedan | C29: WINREG-SD | D29: Window Regulator - SD | E29: LSCBDSD0004 | F29: 1 | G29: pcs | H29: LSC Automobile JP | I29: Japan | J29: SEDAN_001
A30: 2 | B30: Sedan | C30: SEAT-SD | D30: Seat - SD | E30: LSCINSD0005 | F30: 5 | G30: pcs | H30: VN Interiors Ltd | I30: Vietnam | J30: SEDAN_001
A31: 2 | B31: Sedan | C31: FRAMESEAT-SD | D31: Seat Frame - SD | E31: LSCINSD0005 | F31: 1 | G31: pcs | H31: VN Interiors Ltd | I31: Vietnam | J31: SEDAN_001
A32: 2 | B32: Sedan Luxury | C32: CYL-SD - LX | D32: Cylinder Block - SD - LX | E32: LSCENSD0001-LX | F32: 1 | G32: set | H32: LSC Automobile JP | I32: Japan | J32: SEDAN_LUXURY_001
A33: 2 | B33: Sedan Luxury | C33: PIST-SD - LX | D33: Pistons - SD - LX | E33: LSCENSD0001-LX | F33: 4 | G33: pcs | H33: LSC Automobile JP | I33: Japan | J33: SEDAN_LUXURY_001
... A61: 2 | B61: SUV Luxury | C61: FRAMESEAT-SUV - LX | D61: Seat Frame - SUV - LX | E61: LSCINSV0010-LX | F61: 1 | G61: pcs | H61: VN Interiors Ltd | I61: Vietnam | J61: SUV_LUXURY_001

Sheet Sales Forecast
A1: Month | B1: SEDAN_001 | C1: SEDAN_LUXURY_001 | D1: SUV_001 | E1: SUV_LUXURY_001
A2: January | B2: 591 | C2: 401 | D2: 574 | E2: 379
A3: February | B3: 548 | C3: 363 | D3: 544 | E3: 343
A4: March | B4: 601 | C4: 387 | D4: 613 | E4: 409
A5: April | B5: 662 | C5: 451 | D5: 682 | E5: 443
A6: May | B6: 742 | C6: 476 | D6: 737 | E6: 483
A7: June | B7: 828 | C7: 543 | D7: 804 | E7: 545
A8: July | B8: 841 | C8: 571 | D8: 825 | E8: 543
A9: August | B9: 812 | C9: 557 | D9: 826 | E9: 539
A10: September | B10: 732 | C10: 476 | D10: 728 | E10: 502
A11: October | B11: 698 | C11: 472 | D11: 708 | E11: 458
A12: November | B12: 779 | C12: 529 | D12: 764 | E12: 504
A13: December | B13: 959 | C13: 621 | D13: 962 | E13: 644

Sheet Inventory Status
A1: Part Code | B1: Part Name | C1: Parent Assembly Code | D1: Parent Assembly Name | E1: UoM | F1: Supplier | G1: Origin | H1: Production Lead Time (days) | I1: MOQ | J1: Safety Stock Policy | K1: On-hand Qty | L1: On-order Qty | M1: Next Delivery Date | N1: Warehouse | O1: 2026 Open Inventory
A2: DOOR-SD | B2: Door - SD | C2: LSCBDSD0004 | D2: Sedan - SEDAN_001 | E2: pcs | F2: LSC Automobile JP | G2: Japan | H2: 25 | I2: 197 | J2: 346 | K2: 232 | L2: 197 | M2: 45990 | N2: WH-VP-01 | O2: =K2+L2 -> 429
A3: WINREG-SD | B3: Window Regulator - SD | C3: LSCBDSD0004 | D3: Sedan - SEDAN_001 | E3: pcs | F3: LSC Automobile JP | G3: Japan | H3: 29 | I3: 181 | J3: 28 | K3: 691 | L3: 510 | M3: 45969 | N3: WH-SG-01 | O3: =K3+L3 -> 1201
A4: DOOR-SD - LX | B4: Door - SD - LX | C4: LSCBDSD0004-LX | D4: Sedan Luxury - SEDAN_LUXURY_001 | E4: pcs | F4: LSC Automobile JP | G4: Japan | H4: 30 | I4: 11 | J4: 398 | K4: 112 | L4: 345 | M4: 45954 | N4: WH-VP-01 | O4: =K4+L4 -> 457
A5: WINREG-SD - LX | B5: Window Regulator - SD - LX | C5: LSCBDSD0004-LX | D5: Sedan Luxury - SEDAN_LUXURY_001 | E5: pcs | F5: LSC Automobile JP | G5: Japan | H5: 36 | I5: 143 | J5: 280 | K5: 612 | L5: 510 | M5: 46018 | N5: WH-VP-01 | O5: =K5+L5 -> 1122
A6: DOOR-SUV | B6: Door - SUV | C6: LSCBDSV0009 | D6: SUV - SUV_001 | E6: pcs | F6: LSC Automobile JP | G6: Japan | H6: 34 | I6: 199 | J6: 67 | K6: 735 | L6: 297 | M6: 45969 | N6: WH-VP-01 | O6: =K6+L6 -> 1032
A7: WINREG-SUV | B7: Window Regulator - SUV | C7: LSCBDSV0009 | D7: SUV - SUV_001 | E7: pcs | F7: LSC Automobile JP | G7: Japan | H7: 22 | I7: 23 | J7: 81 | K7: 224 | L7: 262 | M7: 45950 | N7: WH-VP-02 | O7: =K7+L7 -> 486
A8: DOOR-SUV - LX | B8: Door - SUV - LX | C8: LSCBDSV0009-LX | D8: SUV Luxury - SUV_LUXURY_001 | E8: pcs | F8: LSC Automobile JP | G8: Japan | H8: 10 | I8: 33 | J8: 120 | K8: 709 | L8: 159 | M8: 45984 | N8: WH-SG-01 | O8: =K8+L8 -> 868
A9: WINREG-SUV - LX | B9: Window Regulator - SUV - LX | C9: LSCBDSV0009-LX | D9: SUV Luxury - SUV_LUXURY_001 | E9: pcs | F9: LSC Automobile JP | G9: Japan | H9: 31 | I9: 163 | J9: 150 | K9: 415 | L9: 8 | M9: 46012 | N9: WH-VP-01 | O9: =K9+L9 -> 423
A10: FRAME-SD | B10: Chassis Frame - SD | C10: LSCCHSD0003 | D10: Sedan - SEDAN_001 | E10: set | F10: LSC Automobile JP | G10: Japan | H10: 27 | I10: 101 | J10: 84 | K10: 607 | L10: 293 | M10: 45956 | N10: WH-VP-02 | O10: =K10+L10 -> 900
A11: MEMBER-SD | B11: Cross Member - SD | C11: LSCCHSD0003 | D11: Sedan - SEDAN_001 | E11: set | F11: LSC Automobile JP | G11: Japan | H11: 45 | I11: 120 | J11: 364 | K11: 471 | L11: 279 | M11: 45960 | N11: WH-VP-02 | O11: =K11+L11 -> 750
A12: FRAME-SD - LX | B12: Chassis Frame - SD - LX | C12: LSCCHSD0003-LX | D12: Sedan Luxury - SEDAN_LUXURY_001 | E12: set | F12: LSC Automobile JP | G12: Japan | H12: 28 | I12: 113 | J12: 182 | K12: 385 | L12: 348 | M12: 46025 | N12: WH-VP-01 | O12: =K12+L12 -> 733
A13: MEMBER-SD - LX | B13: Cross Member - SD - LX | C13: LSCCHSD0003-LX | D13: Sedan Luxury - SEDAN_LUXURY_001 | E13: set | F13: LSC Automobile JP | G13: Japan | H13: 8 | I13: 141 | J13: 308 | K13: 386 | L13: 402 | M13: 45961 | N13: WH-SG-01 | O13: =K13+L13 -> 788
... A41: SYNC-SUV - LX | B41: Synchronizer - SUV - LX | C41: LSCTRSV0007-LX | D41: SUV Luxury - SUV_LUXURY_001 | E41: pcs | F41: LSC Trans VN | G41: Vietnam | H41: 15 | I41: 91 | J41: 233 | K41: 683 | L41: 253 | M41: 46003 | N41: WH-VP-02 | O41: =K41+L41 -> 936

Sheet Assembly Capacity
A1: Product Item Code | B1: Process Step | C1: Monthly Capacity (units)
A2: SEDAN_001 | B2: 1. Stamping | C2: 824
A3: SEDAN_001 | B3: 2. Body/Welding | C3: 834
A4: SEDAN_001 | B4: 3. Paint Shop | C4: 750
A5: SEDAN_001 | B5: 4. Powertrain Sub-assembly | C5: 948
A6: SEDAN_001 | B6: 5. Trim & Final Assembly | C6: 930
A7: SEDAN_001 | B7: 6. QA/Testing & Rework Buffer | C7: 904
A8: SEDAN_LUXURY_001 | B8: 1. Stamping | C8: 591
A9: SEDAN_LUXURY_001 | B9: 2. Body/Welding | C9: 552
A10: SEDAN_LUXURY_001 | B10: 3. Paint Shop | C10: 556
A11: SEDAN_LUXURY_001 | B11: 4. Powertrain Sub-assembly | C11: 631
A12: SEDAN_LUXURY_001 | B12: 5. Trim & Final Assembly | C12: 640
A13: SEDAN_LUXURY_001 | B13: 6. QA/Testing & Rework Buffer | C13: 499
... A25: SUV_LUXURY_001 | B25: 6. QA/Testing & Rework Buffer | C25: 562

Sheet Foreign Suppliers
A1: Part Code | B1: Part Name | C1: Supplier | D1: Country | E1: Factory Capacity (units/month) | F1: Production Lead Time (days) | G1: Shipping Time Tokyo -> Vinh Phuc (days) | H1: FOB Unit Price (USD)
A2: LSCENSD0001 | B2: Engine - SD | C2: LSC Automobile JP | D2: Japan | E2: 15000 | F2: 18 | G2: 12 | H2: 4048.09
A3: LSCCHSD0003 | B3: Chassis - SD | C3: LSC Automobile JP | D3: Japan | E3: 15000 | F3: 18 | G3: 12 | H3: 4048.09
A4: LSCBDSD0004 | B4: Body - SD | C4: LSC Automobile JP | D4: Japan | E4: 15000 | F4: 18 | G4: 12 | H4: 4048.09
A5: LSCENSD0001-LX | B5: Engine - SD - LX | C5: LSC Automobile JP | D5: Japan | E5: 15000 | F5: 18 | G5: 12 | H5: 11025.48
A6: LSCCHSD0003-LX | B6: Chassis - SD - LX | C6: LSC Automobile JP | D6: Japan | E6: 15000 | F6: 18 | G6: 12 | H6: 11025.48
A7: LSCBDSD0004-LX | B7: Body - SD - LX | C7: LSC Automobile JP | D7: Japan | E7: 15000 | F7: 18 | G7: 12 | H7: 11025.48
A8: LSCENSV0006 | B8: Engine - SUV | C8: LSC Automobile JP | D8: Japan | E8: 15000 | F8: 18 | G8: 12 | H8: 5577.37
A9: LSCHSV0008 | B9: Chassis - SUV | C9: LSC Automobile JP | D9: Japan | E9: 15000 | F9: 18 | G9: 12 | H9: 5577.37
A10: LSCBDSV0009 | B10: Body - SUV | C10: LSC Automobile JP | D10: Japan | E10: 15000 | F10: 18 | G10: 12 | H10: 5577.37
A11: LSCENSV0006-LX | B11: Engine - SUV - LX | C11: LSC Automobile JP | D11: Japan | E11: 15000 | F11: 18 | G11: 12 | H11: 8643.97
A12: LSCHSV0008-LX | B12: Chassis - SUV - LX | C12: LSC Automobile JP | D12: Japan | E12: 15000 | F12: 18 | G12: 12 | H12: 8643.97
A13: LSCBDSV0009-LX | B13: Body - SUV - LX | C13: LSC Automobile JP | D13: Japan | E13: 15000 | F13: 18 | G13: 12 | H13: 8643.97
... A37: WINREG-SUV - LX | B37: Window Regulator - SUV - LX | C37: LSC Automobile JP | D37: Japan | E37: 15000 | F37: 18 | G37: 12 | H37: 6786.38

Sheet Local Suppliers
A1: Part Code | B1: Part Name | C1: Supplier | D1: Country | E1: Factory Capacity (units/month) | F1: Production Lead Time (days) | G1: Shipping Time Local Supplier -> Vinh Phuc (days) | H1: EXW Unit Price (USD) | I1: Trucking Bac Giang -> Vinh Phuc (USD/cont) | J1: Factory Unstuffing & Handling (USD/cont) | K1: Local Customs & Admin (USD/cont) | L1: Total Logistics and Handling costs (USD/cont)
A2: LSCTRSD0002 | B2: Transmission - SD | C2: LSC Trans VN | D2: Vietnam | E2: 22000 | F2: 10 | G2: 2 | H2: 2173.3 | I2: 180 | J2: 65 | K2: 40 | L2: =SUM(I2:K2) -> 285
A3: LSCINSD0005 | B3: Interior - SD | C3: VN Interiors Ltd | D3: Vietnam | E3: 22000 | F3: 10 | G3: 2 | H3: 2173.3 | I3: 180 | J3: 65 | K3: 40 | L3: =SUM(I3:K3) -> 285
A4: LSCTRSD0002-LX | B4: Transmission - SD - LX | C4: LSC Trans VN | D4: Vietnam | E4: 22000 | F4: 10 | G4: 2 | H4: 6364.62 | I4: 180 | J4: 65 | K4: 40 | L4: =SUM(I4:K4) -> 285
A5: LSCINSD0005-LX | B5: Interior - SD - LX | C5: VN Interiors Ltd | D5: Vietnam | E5: 22000 | F5: 10 | G5: 2 | H5: 6364.62 | I5: 180 | J5: 65 | K5: 40 | L5: =SUM(I5:K5) -> 285
A6: LSCTRSV0007 | B6: Transmission - SUV | C6: LSC Trans VN | D6: Vietnam | E6: 22000 | F6: 10 | G6: 2 | H6: 2994.32 | I6: 180 | J6: 65 | K6: 40 | L6: =SUM(I6:K6) -> 285
A7: LSCINSV0010 | B7: Interior - SUV | C7: VN Interiors Ltd | D7: Vietnam | E7: 22000 | F7: 10 | G7: 2 | H7: 2994.32 | I7: 180 | J7: 65 | K7: 40 | L7: =SUM(I7:K7) -> 285
A8: LSCTRSV0007-LX | B8: Transmission - SUV - LX | C8: LSC Trans VN | D8: Vietnam | E8: 22000 | F8: 10 | G8: 2 | H8: 4989.86 | I8: 180 | J8: 65 | K8: 40 | L8: =SUM(I8:K8) -> 285
A9: LSCINSV0010-LX | B9: Interior - SUV - LX | C9: VN Interiors Ltd | D9: Vietnam | E9: 22000 | F9: 10 | G9: 2 | H9: 4989.86 | I9: 180 | J9: 65 | K9: 40 | L9: =SUM(I9:K9) -> 285
A10: GEAR-SD | B10: Gear Set - SD | C10: LSC Trans VN | D10: Vietnam | E10: 22000 | F10: 10 | G10: 2 | H10: 302.74 | I10: 180 | J10: 65 | K10: 40 | L10: =SUM(I10:K10) -> 285
A11: SYNC-SD | B11: Synchronizer - SD | C11: LSC Trans VN | D11: Vietnam | E11: 22000 | F11: 10 | G11: 2 | H11: 1870.55 | I11: 180 | J11: 65 | K11: 40 | L11: =SUM(I11:K11) -> 285
A12: SEAT-SD | B12: Seat - SD | C12: VN Interiors Ltd | D12: Vietnam | E12: 22000 | F12: 10 | G12: 2 | H12: 1056.87 | I12: 180 | J12: 65 | K12: 40 | L12: =SUM(I12:K12) -> 285
A13: FRAMESEAT-SD | B13: Seat Frame - SD | C13: VN Interiors Ltd | D13: Vietnam | E13: 22000 | F13: 10 | G13: 2 | H13: 1116.42 | I13: 180 | J13: 65 | K13: 40 | L13: =SUM(I13:K13) -> 285
... A25: FRAMESEAT-SUV - LX | B25: Seat Frame - SUV - LX | C25: VN Interiors Ltd | D25: Vietnam | E25: 22000 | F25: 10 | G25: 2 | H25: 2725.46 | I25: 180 | J25: 65 | K25: 40 | L25: =SUM(I25:K25) -> 285

Sheet Ocean Freight 2026
A1: Month | B1: Freight Rate Tokyo - HPH (USD/40HC) | C1: POL Local Charges (Tokyo, USD/cont) | D1: POD Local Charges (Haiphong, USD/cont) | E1: Lift on/Lift off at HPH (USD/cont) | F1: Trucking HPH → Vinh Phuc (USD/cont) | G1: Factory Unstuffing & Handling (USD/cont) | H1: Customs Brokerage (USD/cont) | I1: Total Logistics & Handling (USD/cont)
A2: Jan | B2: 1737 | C2: 420 | D2: 560 | E2: 70 | F2: 220 | G2: 95 | H2: 70 | I2: 3172
A3: Feb | B3: 1794 | C3: 420 | D3: 560 | E3: 70 | F3: 220 | G3: 95 | H3: 70 | I3: 3229
A4: Mar | B4: 1785 | C4: 420 | D4: 560 | E4: 70 | F4: 220 | G4: 95 | H4: 70 | I4: 3220
A5: Apr | B5: 1889 | C5: 420 | D5: 560 | E5: 70 | F5: 220 | G5: 95 | H5: 70 | I5: 3324
A6: May | B6: 1933 | C6: 420 | D6: 560 | E6: 70 | F6: 220 | G6: 95 | H6: 70 | I6: 3368
A7: Jun | B7: 2021 | C7: 420 | D7: 560 | E7: 70 | F7: 220 | G7: 95 | H7: 70 | I7: 3456
A8: Jul | B8: 2115 | C8: 420 | D8: 560 | E8: 70 | F8: 220 | G8: 95 | H8: 70 | I8: 3550
A9: Aug | B9: 2127 | C9: 420 | D9: 560 | E9: 70 | F9: 220 | G9: 95 | H9: 70 | I9: 3562
A10: Sep | B10: 1969 | C10: 420 | D10: 560 | E10: 70 | F10: 220 | G10: 95 | H10: 70 | I10: 3404
A11: Oct | B11: 1983 | C11: 420 | D11: 560 | E11: 70 | F11: 220 | G11: 95 | H11: 70 | I11: 3418
A12: Nov | B12: 2202 | C12: 420 | D12: 560 | E12: 70 | F12: 220 | G12: 95 | H12: 70 | I12: 3637
A13: Dec | B13: 2442 | C13: 420 | D13: 560 | E13: 70 | F13: 220 | G13: 95 | H13: 70 | I13: 3877

Sheet Parameters
A1: Parameter | B1: Value | C1: Unit | D1: Notes
A2: Default Import Duty Rate (%) | B2: 20 | C2: % | D2: Giả định 20% (dao động 15–20%). Các đội có thể xây chiến lược đăng ký ưu đãi NĐ 26/2023 để giảm dần về 0%.
A3: VAT Rate (%) | B3: 10 | C3: % | D3: Applied on dutiable value per VN customs
A4: Exchange Rate (VND per USD) | B4: 26000 | C4: VND/USD | D4: Planning/budget rate for 2026
A5: Marine Insurance Rate (%) | B5: 0.2 | C5: % | D5: Applied on (FOB + Freight) if buyer insures
A6: Default Container Type | B6: 40HC | D6: Freight rate column is USD/40HC

Sheet Packing Specification
A1: Part Code | B1: Part Name | C1: Units per 40HC
A2: LSCENSD0001 | B2: Engine - SD | C2: 10
A3: LSCCHSD0003 | B3: Chassis - SD | C3: 20
A4: LSCBDSD0004 | B4: Body - SD | C4: 15
A5: LSCENSD0001-LX | B5: Engine - SD - LX | C5: 7
A6: LSCCHSD0003-LX | B6: Chassis - SD - LX | C6: 14
A7: LSCBDSD0004-LX | B7: Body - SD - LX | C7: 10
A8: LSCENSV0006 | B8: Engine - SUV | C8: 10
A9: LSCHSV0008 | B9: Chassis - SUV | C9: 20
A10: LSCBDSV0009 | B10: Body - SUV | C10: 15
A11: LSCENSV0006-LX | B11: Engine - SUV - LX | C11: 7
A12: LSCHSV0008-LX | B12: Chassis - SUV - LX | C12: 14
A13: LSCBDSV0009-LX | B13: Body - SUV - LX | C13: 10
... A61: FRAMESEAT-SUV - LX | B61: Seat Frame - SUV - LX | C61: 35

Sheet TAX
A1: origin_type | B1: insurance | C1: import_duty | D1: VAT
A2: FOB_JP | B2: 0.002 | C2: 0.2 | D2: 0.1
A3: EXW_VN | B3: 0 | C3: 0 | D3: 0.1

Sheet ASSUMPTIONS
A1: ASSUMPTIONS
A2: 1. Opening inventory of FG/L1 in 2026-01 = 0
A3: 2. Capacity of making L1 is unlimited
A4: 3. Holding cost = 20%/year

Sheet BOM_FG_L1
A1: item_level | B1: fg_code (Product Item Code) | C1: l1_code (Assembly Code) | D1: l1_name (Assembly Name) | E1: qty_per_fg (Quantity) | F1: unit
A2: 1 | B2: SEDAN_001 | C2: LSCENSD0001 | D2: Engine - SD | E2: 1 | F2: set
A3: 1 | B3: SEDAN_001 | C3: LSCTRSD0002 | D3: Transmission - SD | E3: 1 | F3: set
A4: 1 | B4: SEDAN_001 | C4: LSCCHSD0003 | D4: Chassis - SD | E4: 1 | F4: set
A5: 1 | B5: SEDAN_001 | C5: LSCBDSD0004 | D5: Body - SD | E5: 1 | F5: set
A6: 1 | B6: SEDAN_001 | C6: LSCINSD0005 | D6: Interior - SD | E6: 1 | F6: set
A7: 1 | B7: SEDAN_LUXURY_001 | C7: LSCENSD0001-LX | D7: Engine - SD - LX | E7: 1 | F7: set
A8: 1 | B8: SEDAN_LUXURY_001 | C8: LSCTRSD0002-LX | D8: Transmission - SD - LX | E8: 1 | F8: set
A9: 1 | B9: SEDAN_LUXURY_001 | C9: LSCCHSD0003-LX | D9: Chassis - SD - LX | E9: 1 | F9: set
A10: 1 | B10: SEDAN_LUXURY_001 | C10: LSCBDSD0004-LX | D10: Body - SD - LX | E10: 1 | F10: set
A11: 1 | B11: SEDAN_LUXURY_001 | C11: LSCINSD0005-LX | D11: Interior - SD - LX | E11: 1 | F11: set
A12: 1 | B12: SUV_001 | C12: LSCENSV0006 | D12: Engine - SUV | E12: 1 | F12: set
A13: 1 | B13: SUV_001 | C13: LSCTRSV0007 | D13: Transmission - SUV | E13: 1 | F13: set
... A21: 1 | B21: SUV_LUXURY_001 | C21: LSCINSV0010-LX | D21: Interior - SUV - LX | E21: 1 | F21: set

Sheet BOM_L1_L2
A1: item_level | B1: l1_code (Parent Code) | C1: l1_name (Parent) | D1: l2_code (Assembly Code) | E1: l2_name (Assembly Name) | F1: qty_per_l1 (Quantity) | G1: unit
A2: 2 | B2: {=XLOOKUP(BOM_L1_L2!$D2,'Bill of Materials'!$C$22:$C$61,'Bill of Materials'!$E$22:$E$61)} -> LSCENSD0001 | C2: {=XLOOKUP(B2,BOM_FG_L1!$C$2:$C$21,BOM_FG_L1!$D$2:$D$21)} -> Engine - SD | D2: CYL-SD | E2: Cylinder Block - SD | F2: 1 | G2: set
A3: 2 | B3: {=XLOOKUP(BOM_L1_L2!$D3,'Bill of Materials'!$C$22:$C$61,'Bill of Materials'!$E$22:$E$61)} -> LSCENSD0001 | C3: {=XLOOKUP(B3,BOM_FG_L1!$C$2:$C$21,BOM_FG_L1!$D$2:$D$21)} -> Engine - SD | D3: PIST-SD | E3: Pistons - SD | F3: 4 | G3: pcs
A4: 2 | B4: {=XLOOKUP(BOM_L1_L2!$D4,'Bill of Materials'!$C$22:$C$61,'Bill of Materials'!$E$22:$E$61)} -> LSCTRSD0002 | C4: {=XLOOKUP(B4,BOM_FG_L1!$C$2:$C$21,BOM_FG_L1!$D$2:$D$21)} -> Transmission - SD | D4: GEAR-SD | E4: Gear Set - SD | F4: 1 | G4: set
A5: 2 | B5: {=XLOOKUP(BOM_L1_L2!$D5,'Bill of Materials'!$C$22:$C$61,'Bill of Materials'!$E$22:$E$61)} -> LSCTRSD0002 | C5: {=XLOOKUP(B5,BOM_FG_L1!$C$2:$C$21,BOM_FG_L1!$D$2:$D$21)} -> Transmission - SD | D5: SYNC-SD | E5: Synchronizer - SD | F5: 1 | G5: pcs
A6: 2 | B6: {=XLOOKUP(BOM_L1_L2!$D6,'Bill of Materials'!$C$22:$C$61,'Bill of Materials'!$E$22:$E$61)} -> LSCCHSD0003 | C6: {=XLOOKUP(B6,BOM_FG_L1!$C$2:$C$21,BOM_FG_L1!$D$2:$D$21)} -> Chassis - SD | D6: FRAME-SD | E6: Chassis Frame - SD | F6: 1 | G6: set
A7: 2 | B7: {=XLOOKUP(BOM_L1_L2!$D7,'Bill of Materials'!$C$22:$C$61,'Bill of Materials'!$E$22:$E$61)} -> LSCCHSD0003 | C7: {=XLOOKUP(B7,BOM_FG_L1!$C$2:$C$21,BOM_FG_L1!$D$2:$D$21)} -> Chassis - SD | D7: MEMBER-SD | E7: Cross Member - SD | F7: 1 | G7: set
A8: 2 | B8: {=XLOOKUP(BOM_L1_L2!$D8,'Bill of Materials'!$C$22:$C$61,'Bill of Materials'!$E$22:$E$61)} -> LSCBDSD0004 | C8: {=XLOOKUP(B8,BOM_FG_L1!$C$2:$C$21,BOM_FG_L1!$D$2:$D$21)} -> Body - SD | D8: DOOR-SD | E8: Door - SD | F8: 5 | G8: pcs
A9: 2 | B9: {=XLOOKUP(BOM_L1_L2!$D9,'Bill of Materials'!$C$22:$C$61,'Bill of Materials'!$E$22:$E$61)} -> LSCBDSD0004 | C9: {=XLOOKUP(B9,BOM_FG_L1!$C$2:$C$21,BOM_FG_L1!$D$2:$D$21)} -> Body - SD | D9: WINREG-SD | E9: Window Regulator - SD | F9: 1 | G9: pcs
A10: 2 | B10: {=XLOOKUP(BOM_L1_L2!$D10,'Bill of Materials'!$C$22:$C$61,'Bill of Materials'!$E$22:$E$61)} -> LSCINSD0005 | C10: {=XLOOKUP(B10,BOM_FG_L1!$C$2:$C$21,BOM_FG_L1!$D$2:$D$21)} -> Interior - SD | D10: SEAT-SD | E10: Seat - SD | F10: 5 | G10: pcs
A11: 2 | B11: {=XLOOKUP(BOM_L1_L2!$D11,'Bill of Materials'!$C$22:$C$61,'Bill of Materials'!$E$22:$E$61)} -> LSCINSD0005 | C11: {=XLOOKUP(B11,BOM_FG_L1!$C$2:$C$21,BOM_FG_L1!$D$2:$D$21)} -> Interior - SD | D11: FRAMESEAT-SD | E11: Seat Frame - SD | F11: 1 | G11: pcs
A12: 2 | B12: {=XLOOKUP(BOM_L1_L2!$D12,'Bill of Materials'!$C$22:$C$61,'Bill of Materials'!$E$22:$E$61)} -> LSCENSD0001-LX | C12: {=XLOOKUP(B12,BOM_FG_L1!$C$2:$C$21,BOM_FG_L1!$D$2:$D$21)} -> Engine - SD - LX | D12: CYL-SD - LX | E12: Cylinder Block - SD - LX | F12: 1 | G12: set
A13: 2 | B13: {=XLOOKUP(BOM_L1_L2!$D13,'Bill of Materials'!$C$22:$C$61,'Bill of Materials'!$E$22:$E$61)} -> LSCENSD0001-LX | C13: {=XLOOKUP(B13,BOM_FG_L1!$C$2:$C$21,BOM_FG_L1!$D$2:$D$21)} -> Engine - SD - LX | D13: PIST-SD - LX | E13: Pistons - SD - LX | F13: 4 | G13: pcs
... A41: 2 | B41: {=XLOOKUP(BOM_L1_L2!$D41,'Bill of Materials'!$C$22:$C$61,'Bill of Materials'!$E$22:$E$61)} -> LSCINSV0010-LX | C41: {=XLOOKUP(B41,BOM_FG_L1!$C$2:$C$21,BOM_FG_L1!$D$2:$D$21)} -> Interior - SUV - LX | D41: FRAMESEAT-SUV - LX | E41: Seat Frame - SUV - LX | F41: 1 | G41: pcs

Sheet DEMAND_FG
A1: month | B1: fg_code | C1: demand_qty
A2: 2026-01 | B2: SEDAN_001 | C2: 591
A3: 2026-01 | B3: SEDAN_LUXURY_001 | C3: 401
A4: 2026-01 | B4: SUV_001 | C4: 574
A5: 2026-01 | B5: SUV_LUXURY_001 | C5: 379
A6: 2026-02 | B6: SEDAN_001 | C6: 548
A7: 2026-02 | B7: SEDAN_LUXURY_001 | C7: 363
A8: 2026-02 | B8: SUV_001 | C8: 544
A9: 2026-02 | B9: SUV_LUXURY_001 | C9: 343
A10: 2026-03 | B10: SEDAN_001 | C10: 601
A11: 2026-03 | B11: SEDAN_LUXURY_001 | C11: 387
A12: 2026-03 | B12: SUV_001 | C12: 613
A13: 2026-03 | B13: SUV_LUXURY_001 | C13: 409
... A49: 2026-12 | B49: SUV_LUXURY_001 | C49: 644

Sheet INV_START
A1: item_code | B1: item_level | C1: on_hand_qty
A2: DOOR-SD | B2: {=XLOOKUP(A2,BOM_L1_L2!$D$2:$D$41,BOM_L1_L2!$A$2:$A$41)} -> 2 | C2: {=XLOOKUP(INV_START!$A2,'Inventory Status'!$A$2:$A$41,'Inventory Status'!$O$2:$O$41)} -> 429
A3: WINREG-SD | B3: {=XLOOKUP(A3,BOM_L1_L2!$D$2:$D$41,BOM_L1_L2!$A$2:$A$41)} -> 2 | C3: {=XLOOKUP(INV_START!$A3,'Inventory Status'!$A$2:$A$41,'Inventory Status'!$O$2:$O$41)} -> 1201
A4: DOOR-SD - LX | B4: {=XLOOKUP(A4,BOM_L1_L2!$D$2:$D$41,BOM_L1_L2!$A$2:$A$41)} -> 2 | C4: {=XLOOKUP(INV_START!$A4,'Inventory Status'!$A$2:$A$41,'Inventory Status'!$O$2:$O$41)} -> 457
A5: WINREG-SD - LX | B5: {=XLOOKUP(A5,BOM_L1_L2!$D$2:$D$41,BOM_L1_L2!$A$2:$A$41)} -> 2 | C5: {=XLOOKUP(INV_START!$A5,'Inventory Status'!$A$2:$A$41,'Inventory Status'!$O$2:$O$41)} -> 1122
A6: DOOR-SUV | B6: {=XLOOKUP(A6,BOM_L1_L2!$D$2:$D$41,BOM_L1_L2!$A$2:$A$41)} -> 2 | C6: {=XLOOKUP(INV_START!$A6,'Inventory Status'!$A$2:$A$41,'Inventory Status'!$O$2:$O$41)} -> 1032
A7: WINREG-SUV | B7: {=XLOOKUP(A7,BOM_L1_L2!$D$2:$D$41,BOM_L1_L2!$A$2:$A$41)} -> 2 | C7: {=XLOOKUP(INV_START!$A7,'Inventory Status'!$A$2:$A$41,'Inventory Status'!$O$2:$O$41)} -> 486
A8: DOOR-SUV - LX | B8: {=XLOOKUP(A8,BOM_L1_L2!$D$2:$D$41,BOM_L1_L2!$A$2:$A$41)} -> 2 | C8: {=XLOOKUP(INV_START!$A8,'Inventory Status'!$A$2:$A$41,'Inventory Status'!$O$2:$O$41)} -> 868
A9: WINREG-SUV - LX | B9: {=XLOOKUP(A9,BOM_L1_L2!$D$2:$D$41,BOM_L1_L2!$A$2:$A$41)} -> 2 | C9: {=XLOOKUP(INV_START!$A9,'Inventory Status'!$A$2:$A$41,'Inventory Status'!$O$2:$O$41)} -> 423
A10: FRAME-SD | B10: {=XLOOKUP(A10,BOM_L1_L2!$D$2:$D$41,BOM_L1_L2!$A$2:$A$41)} -> 2 | C10: {=XLOOKUP(INV_START!$A10,'Inventory Status'!$A$2:$A$41,'Inventory Status'!$O$2:$O$41)} -> 900
A11: MEMBER-SD | B11: {=XLOOKUP(A11,BOM_L1_L2!$D$2:$D$41,BOM_L1_L2!$A$2:$A$41)} -> 2 | C11: {=XLOOKUP(INV_START!$A11,'Inventory Status'!$A$2:$A$41,'Inventory Status'!$O$2:$O$41)} -> 750
A12: FRAME-SD - LX | B12: {=XLOOKUP(A12,BOM_L1_L2!$D$2:$D$41,BOM_L1_L2!$A$2:$A$41)} -> 2 | C12: {=XLOOKUP(INV_START!$A12,'Inventory Status'!$A$2:$A$41,'Inventory Status'!$O$2:$O$41)} -> 733
A13: MEMBER-SD - LX | B13: {=XLOOKUP(A13,BOM_L1_L2!$D$2:$D$41,BOM_L1_L2!$A$2:$A$41)} -> 2 | C13: {=XLOOKUP(INV_START!$A13,'Inventory Status'!$A$2:$A$41,'Inventory Status'!$O$2:$O$41)} -> 788
... A41: SYNC-SUV - LX | B41: {=XLOOKUP(A41,BOM_L1_L2!$D$2:$D$41,BOM_L1_L2!$A$2:$A$41)} -> 2 | C41: {=XLOOKUP(INV_START!$A41,'Inventory Status'!$A$2:$A$41,'Inventory Status'!$O$2:$O$41)} -> 936

Sheet CAP_FG
A1: fg_code | B1: cap_fg_per_month
A2: SEDAN_001 | B2: =MIN('Assembly Capacity'!C2:C7) -> 750
A3: SEDAN_LUXURY_001 | B3: =MIN('Assembly Capacity'!C8:C13) -> 499
A4: SUV_001 | B4: =MIN('Assembly Capacity'!C14:C19) -> 740
A5: SUV_LUXURY_001 | B5: =MIN('Assembly Capacity'!C20:C25) -> 492

Sheet CONTAINER_COST_MONTH
A1: month | B1: FOB_cost_per_containers
A2: 2026-01 | B2: 3172
A3: 2026-02 | B3: 3229
A4: 2026-03 | B4: 3220
A5: 2026-04 | B5: 3324
A6: 2026-05 | B6: 3368
A7: 2026-06 | B7: 3456
A8: 2026-07 | B8: 3550
A9: 2026-08 | B9: 3562
A10: 2026-09 | B10: 3404
A11: 2026-10 | B11: 3418
A12: 2026-11 | B12: 3637
A13: 2026-12 | B13: 3877

Sheet ITEM_MASTER
A1: item_code | B1: item_level | C1: origin_type | D1: unit_material_cost | E1: units_per_container | F1: moq
A2: LSCENSD0001 | B2: {=XLOOKUP(ITEM_MASTER!$A2,'Bill of Materials'!$C$2:$C$61,'Bill of Materials'!$A$2:$A$61)} -> 1 | C2: {=IF(XLOOKUP(ITEM_MASTER!$A2,'Bill of Materials'!$C$2:$C$61,'Bill of Materials'!$I$2:$I$61)="Japan", "FOB_JP", "EXW_VN")} -> FOB_JP | D2: {=IF(ITEM_MASTER!$C2="FOB_JP", XLOOKUP(ITEM_MASTER!$A2,'Foreign Suppliers'!$A$2:$A$37,'Foreign Suppliers'!$H$2:$H$37), XLOOKUP(ITEM_MASTER!$A2, 'Local Suppliers'!$A$2:$A$25, 'Local Suppliers'!$H$2:$H$25))} -> 4048.09 | E2: {=XLOOKUP(ITEM_MASTER!$A2,'Packing Specification'!$A$2:$A$61,'Packing Specification'!$C$2:$C$61)} -> 10 | F2: {=XLOOKUP(ITEM_MASTER!$A2,'Inventory Status'!$A$2:$A$41,'Inventory Status'!$I$2:$I$41,0)} -> 0
A3: LSCTRSD0002 | B3: {=XLOOKUP(ITEM_MASTER!$A3,'Bill of Materials'!$C$2:$C$61,'Bill of Materials'!$A$2:$A$61)} -> 1 | C3: {=IF(XLOOKUP(ITEM_MASTER!$A3,'Bill of Materials'!$C$2:$C$61,'Bill of Materials'!$I$2:$I$61)="Japan", "FOB_JP", "EXW_VN")} -> EXW_VN | D3: {=IF(ITEM_MASTER!$C3="FOB_JP", XLOOKUP(ITEM_MASTER!$A3,'Foreign Suppliers'!$A$2:$A$37,'Foreign Suppliers'!$H$2:$H$37), XLOOKUP(ITEM_MASTER!$A3, 'Local Suppliers'!$A$2:$A$25, 'Local Suppliers'!$H$2:$H$25))} -> 2173.3 | E3: {=XLOOKUP(ITEM_MASTER!$A3,'Packing Specification'!$A$2:$A$61,'Packing Specification'!$C$2:$C$61)} -> 40 | F3: {=XLOOKUP(ITEM_MASTER!$A3,'Inventory Status'!$A$2:$A$41,'Inventory Status'!$I$2:$I$41,0)} -> 0
A4: LSCCHSD0003 | B4: {=XLOOKUP(ITEM_MASTER!$A4,'Bill of Materials'!$C$2:$C$61,'Bill of Materials'!$A$2:$A$61)} -> 1 | C4: {=IF(XLOOKUP(ITEM_MASTER!$A4,'Bill of Materials'!$C$2:$C$61,'Bill of Materials'!$I$2:$I$61)="Japan", "FOB_JP", "EXW_VN")} -> FOB_JP | D4: {=IF(ITEM_MASTER!$C4="FOB_JP", XLOOKUP(ITEM_MASTER!$A4,'Foreign Suppliers'!$A$2:$A$37,'Foreign Suppliers'!$H$2:$H$37), XLOOKUP(ITEM_MASTER!$A4, 'Local Suppliers'!$A$2:$A$25, 'Local Suppliers'!$H$2:$H$25))} -> 4048.09 | E4: {=XLOOKUP(ITEM_MASTER!$A4,'Packing Specification'!$A$2:$A$61,'Packing Specification'!$C$2:$C$61)} -> 20 | F4: {=XLOOKUP(ITEM_MASTER!$A4,'Inventory Status'!$A$2:$A$41,'Inventory Status'!$I$2:$I$41,0)} -> 0
A5: LSCBDSD0004 | B5: {=XLOOKUP(ITEM_MASTER!$A5,'Bill of Materials'!$C$2:$C$61,'Bill of Materials'!$A$2:$A$61)} -> 1 | C5: {=IF(XLOOKUP(ITEM_MASTER!$A5,'Bill of Materials'!$C$2:$C$61,'Bill of Materials'!$I$2:$I$61)="Japan", "FOB_JP", "EXW_VN")} -> FOB_JP | D5: {=IF(ITEM_MASTER!$C5="FOB_JP", XLOOKUP(ITEM_MASTER!$A5,'Foreign Suppliers'!$A$2:$A$37,'Foreign Suppliers'!$H$2:$H$37), XLOOKUP(ITEM_MASTER!$A5, 'Local Suppliers'!$A$2:$A$25, 'Local Suppliers'!$H$2:$H$25))} -> 4048.09 | E5: {=XLOOKUP(ITEM_MASTER!$A5,'Packing Specification'!$A$2:$A$61,'Packing Specification'!$C$2:$C$61)} -> 15 | F5: {=XLOOKUP(ITEM_MASTER!$A5,'Inventory Status'!$A$2:$A$41,'Inventory Status'!$I$2:$I$41,0)} -> 0
A6: LSCINSD0005 | B6: {=XLOOKUP(ITEM_MASTER!$A6,'Bill of Materials'!$C$2:$C$61,'Bill of Materials'!$A$2:$A$61)} -> 1 | C6: {=IF(XLOOKUP(ITEM_MASTER!$A6,'Bill of Materials'!$C$2:$C$61,'Bill of Materials'!$I$2:$I$61)="Japan", "FOB_JP", "EXW_VN")} -> EXW_VN | D6: {=IF(ITEM_MASTER!$C6="FOB_JP", XLOOKUP(ITEM_MASTER!$A6,'Foreign Suppliers'!$A$2:$A$37,'Foreign Suppliers'!$H$2:$H$37), XLOOKUP(ITEM_MASTER!$A6, 'Local Suppliers'!$A$2:$A$25, 'Local Suppliers'!$H$2:$H$25))} -> 2173.3 | E6: {=XLOOKUP(ITEM_MASTER!$A6,'Packing Specification'!$A$2:$A$61,'Packing Specification'!$C$2:$C$61)} -> 120 | F6: {=XLOOKUP(ITEM_MASTER!$A6,'Inventory Status'!$A$2:$A$41,'Inventory Status'!$I$2:$I$41,0)} -> 0
A7: LSCENSD0001-LX | B7: {=XLOOKUP(ITEM_MASTER!$A7,'Bill of Materials'!$C$2:$C$61,'Bill of Materials'!$A$2:$A$61)} -> 1 | C7: {=IF(XLOOKUP(ITEM_MASTER!$A7,'Bill of Materials'!$C$2:$C$61,'Bill of Materials'!$I$2:$I$61)="Japan", "FOB_JP", "EXW_VN")} -> FOB_JP | D7: {=IF(ITEM_MASTER!$C7="FOB_JP", XLOOKUP(ITEM_MASTER!$A7,'Foreign Suppliers'!$A$2:$A$37,'Foreign Suppliers'!$H$2:$H$37), XLOOKUP(ITEM_MASTER!$A7, 'Local Suppliers'!$A$2:$A$25, 'Local Suppliers'!$H$2:$H$25))} -> 11025.48 | E7: {=XLOOKUP(ITEM_MASTER!$A7,'Packing Specification'!$A$2:$A$61,'Packing Specification'!$C$2:$C$61)} -> 7 | F7: {=XLOOKUP(ITEM_MASTER!$A7,'Inventory Status'!$A$2:$A$41,'Inventory Status'!$I$2:$I$41,0)} -> 0
A8: LSCTRSD0002-LX | B8: {=XLOOKUP(ITEM_MASTER!$A8,'Bill of Materials'!$C$2:$C$61,'Bill of Materials'!$A$2:$A$61)} -> 1 | C8: {=IF(XLOOKUP(ITEM_MASTER!$A8,'Bill of Materials'!$C$2:$C$61,'Bill of Materials'!$I$2:$I$61)="Japan", "FOB_JP", "EXW_VN")} -> EXW_VN | D8: {=IF(ITEM_MASTER!$C8="FOB_JP", XLOOKUP(ITEM_MASTER!$A8,'Foreign Suppliers'!$A$2:$A$37,'Foreign Suppliers'!$H$2:$H$37), XLOOKUP(ITEM_MASTER!$A8, 'Local Suppliers'!$A$2:$A$25, 'Local Suppliers'!$H$2:$H$25))} -> 6364.62 | E8: {=XLOOKUP(ITEM_MASTER!$A8,'Packing Specification'!$A$2:$A$61,'Packing Specification'!$C$2:$C$61)} -> 28 | F8: {=XLOOKUP(ITEM_MASTER!$A8,'Inventory Status'!$A$2:$A$41,'Inventory Status'!$I$2:$I$41,0)} -> 0
A9: LSCCHSD0003-LX | B9: {=XLOOKUP(ITEM_MASTER!$A9,'Bill of Materials'!$C$2:$C$61,'Bill of Materials'!$A$2:$A$61)} -> 1 | C9: {=IF(XLOOKUP(ITEM_MASTER!$A9,'Bill of Materials'!$C$2:$C$61,'Bill of Materials'!$I$2:$I$61)="Japan", "FOB_JP", "EXW_VN")} -> FOB_JP | D9: {=IF(ITEM_MASTER!$C9="FOB_JP", XLOOKUP(ITEM_MASTER!$A9,'Foreign Suppliers'!$A$2:$A$37,'Foreign Suppliers'!$H$2:$H$37), XLOOKUP(ITEM_MASTER!$A9, 'Local Suppliers'!$A$2:$A$25, 'Local Suppliers'!$H$2:$H$25))} -> 11025.48 | E9: {=XLOOKUP(ITEM_MASTER!$A9,'Packing Specification'!$A$2:$A$61,'Packing Specification'!$C$2:$C$61)} -> 14 | F9: {=XLOOKUP(ITEM_MASTER!$A9,'Inventory Status'!$A$2:$A$41,'Inventory Status'!$I$2:$I$41,0)} -> 0
A10: LSCBDSD0004-LX | B10: {=XLOOKUP(ITEM_MASTER!$A10,'Bill of Materials'!$C$2:$C$61,'Bill of Materials'!$A$2:$A$61)} -> 1 | C10: {=IF(XLOOKUP(ITEM_MASTER!$A10,'Bill of Materials'!$C$2:$C$61,'Bill of Materials'!$I$2:$I$61)="Japan", "FOB_JP", "EXW_VN")} -> FOB_JP | D10: {=IF(ITEM_MASTER!$C10="FOB_JP", XLOOKUP(ITEM_MASTER!$A10,'Foreign Suppliers'!$A$2:$A$37,'Foreign Suppliers'!$H$2:$H$37), XLOOKUP(ITEM_MASTER!$A10, 'Local Suppliers'!$A$2:$A$25, 'Local Suppliers'!$H$2:$H$25))} -> 11025.48 | E10: {=XLOOKUP(ITEM_MASTER!$A10,'Packing Specification'!$A$2:$A$61,'Packing Specification'!$C$2:$C$61)} -> 10 | F10: {=XLOOKUP(ITEM_MASTER!$A10,'Inventory Status'!$A$2:$A$41,'Inventory Status'!$I$2:$I$41,0)} -> 0
A11: LSCINSD0005-LX | B11: {=XLOOKUP(ITEM_MASTER!$A11,'Bill of Materials'!$C$2:$C$61,'Bill of Materials'!$A$2:$A$61)} -> 1 | C11: {=IF(XLOOKUP(ITEM_MASTER!$A11,'Bill of Materials'!$C$2:$C$61,'Bill of Materials'!$I$2:$I$61)="Japan", "FOB_JP", "EXW_VN")} -> EXW_VN | D11: {=IF(ITEM_MASTER!$C11="FOB_JP", XLOOKUP(ITEM_MASTER!$A11,'Foreign Suppliers'!$A$2:$A$37,'Foreign Suppliers'!$H$2:$H$37), XLOOKUP(ITEM_MASTER!$A11, 'Local Suppliers'!$A$2:$A$25, 'Local Suppliers'!$H$2:$H$25))} -> 6364.62 | E11: {=XLOOKUP(ITEM_MASTER!$A11,'Packing Specification'!$A$2:$A$61,'Packing Specification'!$C$2:$C$61)} -> 84 | F11: {=XLOOKUP(ITEM_MASTER!$A11,'Inventory Status'!$A$2:$A$41,'Inventory Status'!$I$2:$I$41,0)} -> 0
A12: LSCENSV0006 | B12: {=XLOOKUP(ITEM_MASTER!$A12,'Bill of Materials'!$C$2:$C$61,'Bill of Materials'!$A$2:$A$61)} -> 1 | C12: {=IF(XLOOKUP(ITEM_MASTER!$A12,'Bill of Materials'!$C$2:$C$61,'Bill of Materials'!$I$2:$I$61)="Japan", "FOB_JP", "EXW_VN")} -> FOB_JP | D12: {=IF(ITEM_MASTER!$C12="FOB_JP", XLOOKUP(ITEM_MASTER!$A12,'Foreign Suppliers'!$A$2:$A$37,'Foreign Suppliers'!$H$2:$H$37), XLOOKUP(ITEM_MASTER!$A12, 'Local Suppliers'!$A$2:$A$25, 'Local Suppliers'!$H$2:$H$25))} -> 5577.37 | E12: {=XLOOKUP(ITEM_MASTER!$A12,'Packing Specification'!$A$2:$A$61,'Packing Specification'!$C$2:$C$61)} -> 10 | F12: {=XLOOKUP(ITEM_MASTER!$A12,'Inventory Status'!$A$2:$A$41,'Inventory Status'!$I$2:$I$41,0)} -> 0
A13: LSCTRSV0007 | B13: {=XLOOKUP(ITEM_MASTER!$A13,'Bill of Materials'!$C$2:$C$61,'Bill of Materials'!$A$2:$A$61)} -> 1 | C13: {=IF(XLOOKUP(ITEM_MASTER!$A13,'Bill of Materials'!$C$2:$C$61,'Bill of Materials'!$I$2:$I$61)="Japan", "FOB_JP", "EXW_VN")} -> EXW_VN | D13: {=IF(ITEM_MASTER!$C13="FOB_JP", XLOOKUP(ITEM_MASTER!$A13,'Foreign Suppliers'!$A$2:$A$37,'Foreign Suppliers'!$H$2:$H$37), XLOOKUP(ITEM_MASTER!$A13, 'Local Suppliers'!$A$2:$A$25, 'Local Suppliers'!$H$2:$H$25))} -> 2994.32 | E13: {=XLOOKUP(ITEM_MASTER!$A13,'Packing Specification'!$A$2:$A$61,'Packing Specification'!$C$2:$C$61)} -> 40 | F13: {=XLOOKUP(ITEM_MASTER!$A13,'Inventory Status'!$A$2:$A$41,'Inventory Status'!$I$2:$I$41,0)} -> 0
... A61: FRAMESEAT-SUV - LX | B61: {=XLOOKUP(ITEM_MASTER!$A61,'Bill of Materials'!$C$2:$C$61,'Bill of Materials'!$A$2:$A$61)} -> 2 | C61: {=IF(XLOOKUP(ITEM_MASTER!$A61,'Bill of Materials'!$C$2:$C$61,'Bill of Materials'!$I$2:$I$61)="Japan", "FOB_JP", "EXW_VN")} -> EXW_VN | D61: {=IF(ITEM_MASTER!$C61="FOB_JP", XLOOKUP(ITEM_MASTER!$A61,'Foreign Suppliers'!$A$2:$A$37,'Foreign Suppliers'!$H$2:$H$37), XLOOKUP(ITEM_MASTER!$A61, 'Local Suppliers'!$A$2:$A$25, 'Local Suppliers'!$H$2:$H$25))} -> 2725.46 | E61: {=XLOOKUP(ITEM_MASTER!$A61,'Packing Specification'!$A$2:$A$61,'Packing Specification'!$C$2:$C$61)} -> 35 | F61: {=XLOOKUP(ITEM_MASTER!$A61,'Inventory Status'!$A$2:$A$41,'Inventory Status'!$I$2:$I$41,0)} -> 133

Sheet COST_BUY_MONTHLY
A1: month | B1: item_code | C1: origin_type | D1: unit_material_cost | E1: units_per_container | F1: container_cost | G1: unit_logistics_cost | H1: insurance | I1: import_duty | J1: VAT | K1: landed_cost_per_unit
A2: 2026-01 | B2: LSCENSD0001 | C2: FOB_JP | D2: 4048.09 | E2: 10 | F2: {=IF(C2 ="FOB_JP", XLOOKUP(A2,CONTAINER_COST_MONTH!$A$2:$A$13,CONTAINER_COST_MONTH!$B$2:$B$13), 285)} -> 3172 | G2: =F2/E2 -> 317.2 | H2: {=XLOOKUP(COST_BUY_MONTHLY!$C2,TAX!$A$2:$A$3,TAX!$B$2:$B$3)} -> 0.002 | I2: {=XLOOKUP(COST_BUY_MONTHLY!$C2,TAX!$A$2:$A$3,TAX!$C$2:$C$3)} -> 0.2 | J2: {=XLOOKUP(COST_BUY_MONTHLY!$C2,TAX!$A$2:$A$3,TAX!$D$2:$D$3)} -> 0.1 | K2: =(D2+G2)*(1+H2)*(1+I2)*(1+J2) -> 5773.7072
A3: 2026-01 | B3: LSCTRSD0002 | C3: EXW_VN | D3: 2173.3 | E3: 40 | F3: {=IF(C3 ="FOB_JP", XLOOKUP(A3,CONTAINER_COST_MONTH!$A$2:$A$13,CONTAINER_COST_MONTH!$B$2:$B$13), 285)} -> 285 | G3: =F3/E3 -> 7.125 | H3: {=XLOOKUP(COST_BUY_MONTHLY!$C3,TAX!$A$2:$A$3,TAX!$B$2:$B$3)} -> 0 | I3: {=XLOOKUP(COST_BUY_MONTHLY!$C3,TAX!$A$2:$A$3,TAX!$C$2:$C$3)} -> 0 | J3: {=XLOOKUP(COST_BUY_MONTHLY!$C3,TAX!$A$2:$A$3,TAX!$D$2:$D$3)} -> 0.1 | K3: =(D3+G3)*(1+H3)*(1+I3)*(1+J3) -> 2398.4675
A4: 2026-01 | B4: LSCCHSD0003 | C4: FOB_JP | D4: 4048.09 | E4: 20 | F4: {=IF(C4 ="FOB_JP", XLOOKUP(A4,CONTAINER_COST_MONTH!$A$2:$A$13,CONTAINER_COST_MONTH!$B$2:$B$13), 285)} -> 3172 | G4: =F4/E4 -> 158.6 | H4: {=XLOOKUP(COST_BUY_MONTHLY!$C4,TAX!$A$2:$A$3,TAX!$B$2:$B$3)} -> 0.002 | I4: {=XLOOKUP(COST_BUY_MONTHLY!$C4,TAX!$A$2:$A$3,TAX!$C$2:$C$3)} -> 0.2 | J4: {=XLOOKUP(COST_BUY_MONTHLY!$C4,TAX!$A$2:$A$3,TAX!$D$2:$D$3)} -> 0.1 | K4: =(D4+G4)*(1+H4)*(1+I4)*(1+J4) -> 5563.9365
A5: 2026-01 | B5: LSCBDSD0004 | C5: FOB_JP | D5: 4048.09 | E5: 15 | F5: {=IF(C5 ="FOB_JP", XLOOKUP(A5,CONTAINER_COST_MONTH!$A$2:$A$13,CONTAINER_COST_MONTH!$B$2:$B$13), 285)} -> 3172 | G5: =F5/E5 -> 211.46667 | H5: {=XLOOKUP(COST_BUY_MONTHLY!$C5,TAX!$A$2:$A$3,TAX!$B$2:$B$3)} -> 0.002 | I5: {=XLOOKUP(COST_BUY_MONTHLY!$C5,TAX!$A$2:$A$3,TAX!$C$2:$C$3)} -> 0.2 | J5: {=XLOOKUP(COST_BUY_MONTHLY!$C5,TAX!$A$2:$A$3,TAX!$D$2:$D$3)} -> 0.1 | K5: =(D5+G5)*(1+H5)*(1+I5)*(1+J5) -> 5633.86
A6: 2026-01 | B6: LSCINSD0005 | C6: EXW_VN | D6: 2173.3 | E6: 120 | F6: {=IF(C6 ="FOB_JP", XLOOKUP(A6,CONTAINER_COST_MONTH!$A$2:$A$13,CONTAINER_COST_MONTH!$B$2:$B$13), 285)} -> 285 | G6: =F6/E6 -> 2.375 | H6: {=XLOOKUP(COST_BUY_MONTHLY!$C6,TAX!$A$2:$A$3,TAX!$B$2:$B$3)} -> 0 | I6: {=XLOOKUP(COST_BUY_MONTHLY!$C6,TAX!$A$2:$A$3,TAX!$C$2:$C$3)} -> 0 | J6: {=XLOOKUP(COST_BUY_MONTHLY!$C6,TAX!$A$2:$A$3,TAX!$D$2:$D$3)} -> 0.1 | K6: =(D6+G6)*(1+H6)*(1+I6)*(1+J6) -> 2393.2425
A7: 2026-01 | B7: LSCENSD0001-LX | C7: FOB_JP | D7: 11025.48 | E7: 7 | F7: {=IF(C7 ="FOB_JP", XLOOKUP(A7,CONTAINER_COST_MONTH!$A$2:$A$13,CONTAINER_COST_MONTH!$B$2:$B$13), 285)} -> 3172 | G7: =F7/E7 -> 453.14286 | H7: {=XLOOKUP(COST_BUY_MONTHLY!$C7,TAX!$A$2:$A$3,TAX!$B$2:$B$3)} -> 0.002 | I7: {=XLOOKUP(COST_BUY_MONTHLY!$C7,TAX!$A$2:$A$3,TAX!$C$2:$C$3)} -> 0.2 | J7: {=XLOOKUP(COST_BUY_MONTHLY!$C7,TAX!$A$2:$A$3,TAX!$D$2:$D$3)} -> 0.1 | K7: =(D7+G7)*(1+H7)*(1+I7)*(1+J7) -> 15182.086
A8: 2026-01 | B8: LSCTRSD0002-LX | C8: EXW_VN | D8: 6364.62 | E8: 28 | F8: {=IF(C8 ="FOB_JP", XLOOKUP(A8,CONTAINER_COST_MONTH!$A$2:$A$13,CONTAINER_COST_MONTH!$B$2:$B$13), 285)} -> 285 | G8: =F8/E8 -> 10.178571 | H8: {=XLOOKUP(COST_BUY_MONTHLY!$C8,TAX!$A$2:$A$3,TAX!$B$2:$B$3)} -> 0 | I8: {=XLOOKUP(COST_BUY_MONTHLY!$C8,TAX!$A$2:$A$3,TAX!$C$2:$C$3)} -> 0 | J8: {=XLOOKUP(COST_BUY_MONTHLY!$C8,TAX!$A$2:$A$3,TAX!$D$2:$D$3)} -> 0.1 | K8: =(D8+G8)*(1+H8)*(1+I8)*(1+J8) -> 7012.2784
A9: 2026-01 | B9: LSCCHSD0003-LX | C9: FOB_JP | D9: 11025.48 | E9: 14 | F9: {=IF(C9 ="FOB_JP", XLOOKUP(A9,CONTAINER_COST_MONTH!$A$2:$A$13,CONTAINER_COST_MONTH!$B$2:$B$13), 285)} -> 3172 | G9: =F9/E9 -> 226.57143 | H9: {=XLOOKUP(COST_BUY_MONTHLY!$C9,TAX!$A$2:$A$3,TAX!$B$2:$B$3)} -> 0.002 | I9: {=XLOOKUP(COST_BUY_MONTHLY!$C9,TAX!$A$2:$A$3,TAX!$C$2:$C$3)} -> 0.2 | J9: {=XLOOKUP(COST_BUY_MONTHLY!$C9,TAX!$A$2:$A$3,TAX!$D$2:$D$3)} -> 0.1 | K9: =(D9+G9)*(1+H9)*(1+I9)*(1+J9) -> 14882.413
A10: 2026-01 | B10: LSCBDSD0004-LX | C10: FOB_JP | D10: 11025.48 | E10: 10 | F10: {=IF(C10 ="FOB_JP", XLOOKUP(A10,CONTAINER_COST_MONTH!$A$2:$A$13,CONTAINER_COST_MONTH!$B$2:$B$13), 285)} -> 3172 | G10: =F10/E10 -> 317.2 | H10: {=XLOOKUP(COST_BUY_MONTHLY!$C10,TAX!$A$2:$A$3,TAX!$B$2:$B$3)} -> 0.002 | I10: {=XLOOKUP(COST_BUY_MONTHLY!$C10,TAX!$A$2:$A$3,TAX!$C$2:$C$3)} -> 0.2 | J10: {=XLOOKUP(COST_BUY_MONTHLY!$C10,TAX!$A$2:$A$3,TAX!$D$2:$D$3)} -> 0.1 | K10: =(D10+G10)*(1+H10)*(1+I10)*(1+J10) -> 15002.282
A11: 2026-01 | B11: LSCINSD0005-LX | C11: EXW_VN | D11: 6364.62 | E11: 84 | F11: {=IF(C11 ="FOB_JP", XLOOKUP(A11,CONTAINER_COST_MONTH!$A$2:$A$13,CONTAINER_COST_MONTH!$B$2:$B$13), 285)} -> 285 | G11: =F11/E11 -> 3.3928571 | H11: {=XLOOKUP(COST_BUY_MONTHLY!$C11,TAX!$A$2:$A$3,TAX!$B$2:$B$3)} -> 0 | I11: {=XLOOKUP(COST_BUY_MONTHLY!$C11,TAX!$A$2:$A$3,TAX!$C$2:$C$3)} -> 0 | J11: {=XLOOKUP(COST_BUY_MONTHLY!$C11,TAX!$A$2:$A$3,TAX!$D$2:$D$3)} -> 0.1 | K11: =(D11+G11)*(1+H11)*(1+I11)*(1+J11) -> 7004.8141
A12: 2026-01 | B12: LSCENSV0006 | C12: FOB_JP | D12: 5577.37 | E12: 10 | F12: {=IF(C12 ="FOB_JP", XLOOKUP(A12,CONTAINER_COST_MONTH!$A$2:$A$13,CONTAINER_COST_MONTH!$B$2:$B$13), 285)} -> 3172 | G12: =F12/E12 -> 317.2 | H12: {=XLOOKUP(COST_BUY_MONTHLY!$C12,TAX!$A$2:$A$3,TAX!$B$2:$B$3)} -> 0.002 | I12: {=XLOOKUP(COST_BUY_MONTHLY!$C12,TAX!$A$2:$A$3,TAX!$C$2:$C$3)} -> 0.2 | J12: {=XLOOKUP(COST_BUY_MONTHLY!$C12,TAX!$A$2:$A$3,TAX!$D$2:$D$3)} -> 0.1 | K12: =(D12+G12)*(1+H12)*(1+I12)*(1+J12) -> 7796.3941
A13: 2026-01 | B13: LSCTRSV0007 | C13: EXW_VN | D13: 2994.32 | E13: 40 | F13: {=IF(C13 ="FOB_JP", XLOOKUP(A13,CONTAINER_COST_MONTH!$A$2:$A$13,CONTAINER_COST_MONTH!$B$2:$B$13), 285)} -> 285 | G13: =F13/E13 -> 7.125 | H13: {=XLOOKUP(COST_BUY_MONTHLY!$C13,TAX!$A$2:$A$3,TAX!$B$2:$B$3)} -> 0 | I13: {=XLOOKUP(COST_BUY_MONTHLY!$C13,TAX!$A$2:$A$3,TAX!$C$2:$C$3)} -> 0 | J13: {=XLOOKUP(COST_BUY_MONTHLY!$C13,TAX!$A$2:$A$3,TAX!$D$2:$D$3)} -> 0.1 | K13: =(D13+G13)*(1+H13)*(1+I13)*(1+J13) -> 3301.5895
... A721: 2026-12 | B721: FRAMESEAT-SUV - LX | C721: EXW_VN | D721: 2725.46 | E721: 35 | F721: {=IF(C721 ="FOB_JP", XLOOKUP(A721,CONTAINER_COST_MONTH!$A$2:$A$13,CONTAINER_COST_MONTH!$B$2:$B$13), 285)} -> 285 | G721: =F721/E721 -> 8.1428571 | H721: {=XLOOKUP(COST_BUY_MONTHLY!$C721,TAX!$A$2:$A$3,TAX!$B$2:$B$3)} -> 0 | I721: {=XLOOKUP(COST_BUY_MONTHLY!$C721,TAX!$A$2:$A$3,TAX!$C$2:$C$3)} -> 0 | J721: {=XLOOKUP(COST_BUY_MONTHLY!$C721,TAX!$A$2:$A$3,TAX!$D$2:$D$3)} -> 0.1 | K721: =(D721+G721)*(1+H721)*(1+I721)*(1+J721) -> 3006.9631
